pyrogg.cpython-33m.so
.libspyrogg/libgomp-c0bd41c1.so.1.0.0
pyrogg-0.3.dist-info/METADATA
pyrogg-0.3.dist-info/top_level.txt
pyrogg-0.3.dist-info/DESCRIPTION.rst
pyrogg-0.3.dist-info/metadata.json
pyrogg-0.3.dist-info/RECORD
pyrogg-0.3.dist-info/WHEEL
