Metadata-Version: 1.1
Name: pyrogg
Version: 0.3
Summary: Recode Ogg-Vorbis files to a different quality level
Home-page: https://github.com/scoder/pyrogg
Author: pyrogg dev team
Author-email: stefan_ml@behnel.de
License: UNKNOWN
Platform: UNKNOWN
Classifier: Development Status :: 4 - Beta
Classifier: Intended Audience :: Developers
Classifier: Intended Audience :: Information Technology
Classifier: License :: OSI Approved :: BSD License
Classifier: Programming Language :: Cython
Classifier: Programming Language :: Python :: 2
Classifier: Programming Language :: Python :: 3
Classifier: Operating System :: OS Independent
Classifier: Topic :: Multimedia :: Sound/Audio
